topsis_vikas/__init__.py
topsis_vikas/topsis.py
topsis_vikas_102303451-1.0.1.dist-info/licenses/LICENSE
topsis_vikas_102303451-1.0.1.dist-info/METADATA
topsis_vikas_102303451-1.0.1.dist-info/WHEEL
topsis_vikas_102303451-1.0.1.dist-info/entry_points.txt
topsis_vikas_102303451-1.0.1.dist-info/top_level.txt
topsis_vikas_102303451-1.0.1.dist-info/RECORD
