Metadata-Version: 2.4
Name: Topsis-Vikas-102303451
Version: 1.0.1
Summary: A Python package for TOPSIS implementation
Home-page: https://github.com/vikasverma/topsis
Author: Vikas Verma
Author-email: vverma_be22@thapar.edu
Classifier: Programming Language :: Python :: 3
Classifier: License :: OSI Approved :: MIT License
Classifier: Operating System :: OS Independent
Requires-Python: >=3.6
License-File: LICENSE
Dynamic: author
Dynamic: author-email
Dynamic: classifier
Dynamic: description
Dynamic: description-content-type
Dynamic: home-page
Dynamic: license-file
Dynamic: requires-python
Dynamic: summary
